wrapt/__init__.py
wrapt/__init__.pyi
wrapt/__wrapt__.py
wrapt/_wrappers.c
wrapt/arguments.py
wrapt/decorators.py
wrapt/importer.py
wrapt/patches.py
wrapt/proxies.py
wrapt/py.typed
wrapt/weakrefs.py
wrapt/wrappers.py
wrapt-2.1.0.dist-info/licenses/LICENSE
wrapt-2.1.0.dist-info/METADATA
wrapt-2.1.0.dist-info/WHEEL
wrapt-2.1.0.dist-info/top_level.txt
wrapt-2.1.0.dist-info/RECORD
