Metadata-Version: 2.4
Name: wrapt
Version: 2.1.0
Summary: Module for decorators, wrappers and monkey patching.
Author-email: Graham Dumpleton <Graham.Dumpleton@gmail.com>
License-Expression: BSD-2-Clause
Project-URL: Homepage, https://github.com/GrahamDumpleton/wrapt
Project-URL: Bug Tracker, https://github.com/GrahamDumpleton/wrapt/issues/
Project-URL: Changelog, https://wrapt.readthedocs.io/en/latest/changes.html
Project-URL: Documentation, https://wrapt.readthedocs.io/
Keywords: wrapper,proxy,decorator
Classifier: Development Status :: 5 - Production/Stable
Classifier: Programming Language :: Python :: 3
Classifier: Programming Language :: Python :: 3.9
Classifier: Programming Language :: Python :: 3.10
Classifier: Programming Language :: Python :: 3.11
Classifier: Programming Language :: Python :: 3.12
Classifier: Programming Language :: Python :: 3.13
Classifier: Programming Language :: Python :: 3.14
Classifier: Programming Language :: Python :: Implementation :: CPython
Classifier: Programming Language :: Python :: Implementation :: PyPy
Requires-Python: >=3.9
License-File: LICENSE
Provides-Extra: dev
Requires-Dist: pytest; extra == "dev"
Requires-Dist: setuptools; extra == "dev"
Dynamic: license-file
